oiadb/__init__.py
oiadb/adb.py
oiadb/examples.py
oiadb/examples_image_recognition.py
oiadb/exceptions.py
oiadb/commands/__init__.py
oiadb/commands/android14_support.py
oiadb/commands/app_info.py
oiadb/commands/apps.py
oiadb/commands/basic.py
oiadb/commands/commands.py
oiadb/commands/connect.py
oiadb/commands/core.py
oiadb/commands/device_actions.py
oiadb/commands/device_info.py
oiadb/commands/file_ops.py
oiadb/commands/image_interaction.py
oiadb/commands/interaction.py
oiadb/commands/logs.py
oiadb/commands/permissions.py
oiadb/commands/ui_compatibility.py
oiadb/commands/xml_dump.py
oiadb-0.6.3.dist-info/licenses/LICENSE
oiadb-0.6.3.dist-info/METADATA
oiadb-0.6.3.dist-info/WHEEL
oiadb-0.6.3.dist-info/top_level.txt
oiadb-0.6.3.dist-info/RECORD
