Metadata-Version: 2.4
Name: oiadb
Version: 0.6.3
Summary: ADB Python wrapper library with enhanced functionality, image recognition and multiplatform support
Home-page: https://github.com/tiendung102k3/oiadb
Author: Tien Dung
Author-email: example@example.com
Project-URL: Bug Reports, https://github.com/tiendung102k3/oiadb/issues
Project-URL: Source, https://github.com/tiendung102k3/oiadb
Keywords: adb,android,debug,bridge,automation,testing,image recognition,opencv,uiautomator,multiplatform,windows,linux,macos,termux
Classifier: Development Status :: 4 - Beta
Classifier: Intended Audience :: Developers
Classifier: License :: OSI Approved :: MIT License
Classifier: Programming Language :: Python :: 3
Classifier: Programming Language :: Python :: 3.6
Classifier: Programming Language :: Python :: 3.7
Classifier: Programming Language :: Python :: 3.8
Classifier: Programming Language :: Python :: 3.9
Classifier: Programming Language :: Python :: 3.10
Classifier: Programming Language :: Python :: 3.11
Classifier: Programming Language :: Python :: 3.12
Classifier: Topic :: Software Development :: Testing
Classifier: Topic :: Software Development :: Libraries
Classifier: Operating System :: Microsoft :: Windows
Classifier: Operating System :: POSIX :: Linux
Classifier: Operating System :: MacOS :: MacOS X
Requires-Python: >=3.6
License-File: LICENSE
Requires-Dist: requests>=2.20
Provides-Extra: image
Requires-Dist: opencv-python>=4.5.0; extra == "image"
Requires-Dist: numpy>=1.19.0; extra == "image"
Dynamic: author
Dynamic: author-email
Dynamic: classifier
Dynamic: description
Dynamic: description-content-type
Dynamic: home-page
Dynamic: keywords
Dynamic: license-file
Dynamic: project-url
Dynamic: provides-extra
Dynamic: requires-dist
Dynamic: requires-python
Dynamic: summary
